{
  "pr_number": 1155,
  "summary": "AI活用による3-15歳一貫教育で基礎教育を短縮し早期社会参加を実現する抜本的教育改革",
  "category": "制度・システム",
  "specificity": {
    "level": "高",
    "reason": "年齢設定、海外事例、リサーチパーク構想など具体的な実施内容を明記"
  },
  "difficulty": {
    "level": "高",
    "main_challenge": "教育基本法等の大幅改正と社会全体の価値観転換が必要"
  },
  "scope": "全国",
  "required_resources": "制度改正",
  "keywords": ["AI教育", "個別最適化", "早期教育", "リサーチパーク", "少子化対策"],
  "unique_features": "15歳での基礎教育修了と早期社会参加を目指す革新的提案",
  "discussion_points": ["3歳からの義務教育開始の是非と実現可能性", "15歳での基礎教育修了後の進路保障とキャリア形成"]
}
