{
  "additions": 1,
  "author": {
    "is_bot": true,
    "login": "app/idobata-policy-app"
  },
  "body": "二児の親さんの貴重なご提案に基づき、現行の教育政策マニフェスト「１．教育」に関して、より実効性の高いものとするための改善案を提案させていただきます。\n\n**主な変更点と内容:**\n今回の変更は、「１）一人ひとりに合わせたオーダーメイドカリキュラムを届けます」の「政策概要」セクションに、新たなテスト制度の導入を明記するものです。具体的には、現行案にある義務教育段階終了時のテストに加え、**各学年が終了し次の学年に進級するタイミングで、毎年到達度を確認するためのテストを実施する**という内容を追記いたしました。\n\n**変更の意図・目的:**\nこの変更の根本的な目的は、児童生徒一人ひとりの学習状況をより早期かつ継続的に把握し、個々に応じた最適な教育支援を提供することで、誰一人取り残されることのない教育環境を実現することにあります。\n\n1.  **早期かつ継続的な課題発見と個別最適化された対応の実現:**\n    毎年のテストを通じて、生徒ごとの学習理解度やつまずきのポイントを早期に、かつ経年変化として捉えることが可能になります。例えば、ある特定の教科の特定単元で理解が不十分であると判断された場合、AIを活用したオーダーメイドカリキュラムが即座に調整され、当該生徒専用の補習教材や個別指導プランが提案されます。また、教員はこれらのデータを基に、対象生徒へのきめ細やかな声かけや指導方法の工夫を行うことができます。これにより、問題が深刻化する前に、きめ細やかな対応を行うことができます。\n\n2.  **次学年へのスムーズな連携と「学び残し」の解消:**\n    テスト結果は、単にその時点での評価に留まらず、次学年の学習計画に具体的に活かされます。例えば、前学年の特定領域で課題が残った生徒に対しては、新学年の授業開始前に特別な導入プログラムを提供したり、関連する基礎事項を重点的に復習できるような教材を組み合わせたりすることが考えられます。これにより、生徒が自信を持って新しい学年の学習に取り組めるよう支援し、「学び残し」による継続的な学力低下を防ぎます。\n\n3.  **教育プログラム全体の質の向上とEBPM（証拠に基づく政策立案）の深化:**\n    全生徒のテスト結果を匿名化し集積・分析することで、学校単位、地域単位、さらには国全体としての教育課程や指導方法の有効性を客観的に評価できます。特定の指導法が高い効果を示している事例や、多くの生徒がつまずきやすい共通の課題などが明らかになれば、それらをカリキュラム改善や教員研修プログラムの開発に活かすことができます。これにより、個々の経験則に頼るのではなく、具体的なデータに基づいた政策改善サイクル（EBPM）を教育現場で本格的に推進し、教育システム全体の質の向上を目指します。\n\n**提案の背景:**\nこの提案は、ユーザーである二児の親さんから提起された、「義務教育段階終了時の一度のテストだけでは、結果が悪かった生徒へのフォローアップが手遅れになるのではないか。また、学校の取り組みの成否を最終段階で判断するだけでは、途中の改善機会を逃してしまうのではないか」という非常に重要な懸念に基づいています。このご指摘は、子どもの成長は継続的なプロセスであり、その時々に応じたきめ細やかなサポートが不可欠であるという教育の本質に関わるものです。現行案の最終テストの意義を認めつつも、それだけでは不十分であるとの認識から、より予防的かつ形成的評価の観点を取り入れるべく、今回の学年ごとのテスト導入に至りました。\n\n**期待される効果と展望:**\nこの改善提案が実現することにより、児童生徒は自らの学習進度や課題を具体的に把握し、主体的に学習に取り組むモチベーションを高めることが期待できます。また、教員はデータに基づいたより効果的な指導を行うことが可能となり、学校全体としての教育力の向上が見込まれます。長期的には、国内の教育格差の縮小や、国際的な学力水準の向上にも貢献しうると考えます。\n\nこの提案が、日本の子どもたちの未来にとって、より良い教育環境を築く一助となることを願っております。皆様からの建設的なご意見を心よりお待ちしております。\n\n（ユーザー名：二児の親）",
  "changedFiles": 1,
  "comments": [],
  "createdAt": "2025-06-18T01:10:35Z",
  "deletions": 1,
  "labels": [
    {
      "id": "LA_kwDOOqTJvM8AAAACAn5d8w",
      "name": "教育",
      "description": "",
      "color": "E57B81"
    }
  ],
  "mergeable": "MERGEABLE",
  "mergedAt": null,
  "number": 2578,
  "reactionGroups": [],
  "state": "OPEN",
  "title": "教育政策改善：学年ごとの到達度確認テスト導入による早期学習支援の強化",
  "updatedAt": "2025-06-18T15:20:41Z",
  "url": "https://github.com/team-mirai/policy/pull/2578",
  "commentsCount": 0,
  "totalReactions": 0
}