{
  "additions": 15,
  "author": {
    "is_bot": true,
    "login": "app/idobata-policy-app"
  },
  "body": "本提案は、くろねこさんからのご意見に基づき、マニフェストに「生涯学習」と「社会全体の教育への理解」という視点を加えるものです。具体的には、「社会人の学びをアップデートする環境整備」と「教育内容の可視化」を新たに提案します。これは、個人の成長支援に留まらず、より安全で健全な労働環境の実現と、世代間の分断解消を目指す、社会全体のアップデート施策です。\n\n**【背景と課題意識】**\n\n1.  **知識格差が生む、社会の分断とリスク:**\n    AIやIT技術が進化する一方、その知識は世代や企業規模により大きな偏りがあります。この格差は経済的なものだけでなく、ハラスメントや価値観の対立など、社会的な分断やリスクを生む温床となっています。特に中小企業や個人事業主では研修機会が乏しく、働く個人の意欲だけでは解決が困難な状況です。\n\n2.  **教育のブラックボックス化が招く、世代間の断絶と不信:**\n    子どもを持たない世帯にとって、現在の公教育でどのような内容が教えられているのかを知る機会はほとんどありません。教育が「ブラックボックス」化することで、税金の使途に対する不信感や、教育への無関心が生じやすくなっています。また、「Z世代」といったレッテルだけで若者を判断するなど、異なる教育背景を持つ世代間の相互理解を阻む一因にもなっています。\n\n**【具体的な提案内容】**\n\n1.  **社会人の学びをアップデートする環境の整備（新規項目追加）:**\n    *   **国の役割① - 基礎プログラムの提供:**\n        国は、全ての社会人が最低限押さえておくべき知識（AI・ITリテラシー、ジェンダー、育児参加など）を学べるオンラインプログラムを創設します。教材は、別途提案されている「キャリア支援プラットフォーム」と連携し、各分野の専門家チームが開発することで、質の高さを担保します。特に中小企業や個人事業主が活用しやすいように、これは原則無料とします。\n    *   **国の役割② - 学習推進企業の認証制度の創設:**\n        既存の研修サービス市場との公正な競争を維持しつつ、社会全体の学習を促進するため、新たな認証制度を創設します。国のプログラムの利用有無にかかわらず、同等またはそれ以上の水準の研修を社員に提供している企業（個人事業主を含む）を国が認証し、そのリストを公表します。認証された企業には、ウェブサイト等で活用できるロゴマークを配布します。\n    *   **期待される効果:**\n        この認証制度により、求職者は「社員のリテラシー水準が高く、ハラスメントリスクの少ない健全な職場」という新しい客観的な指標で企業を選べるようになります。企業側も、人材投資に積極的な姿勢をアピールでき、採用力強化に繋がります。国が直接サービスを独占するのではなく、民間と協調して社会全体の労働環境の質的向上を目指します。\n\n2.  **教育の可視化（既存項目への追記）:**\n    「１）政府全体で、教育への投資予算を確保します」の政策概要に、「どのような教育が実施されているかを可視化する」方針を明記します。これにより、希望する国民は誰でも、現在の子どもたちが受けている教育の現状を知ることができるようになります。これは、教育への国民全体の理解と信頼を深め、世代間の健全な対話を生むための共通の土台となります。\n\nこれらの提案は、マニフェストが掲げる「人への投資」というビジョンを、子どもたちだけでなく、全ての世代へと広げるものです。社会全体の知的資本を向上させ、分断のない、しなやかで強い社会を構築するために、本変更案をご審議ください。\n\n（提案者：くろねこ）",
  "changedFiles": 1,
  "comments": [],
  "createdAt": "2025-07-08T06:50:31Z",
  "deletions": 4,
  "labels": [
    {
      "id": "LA_kwDOOqTJvM8AAAACAn5d8w",
      "name": "教育",
      "description": "",
      "color": "E57B81"
    }
  ],
  "mergeable": "MERGEABLE",
  "mergedAt": null,
  "number": 4489,
  "reactionGroups": [],
  "state": "OPEN",
  "title": "教育：社会人の学びと労働環境改善に関する認証制度の提案",
  "updatedAt": "2025-07-08T15:21:57Z",
  "url": "https://github.com/team-mirai/policy/pull/4489",
  "commentsCount": 0,
  "totalReactions": 0
}