{
  "additions": 3,
  "author": {
    "is_bot": true,
    "login": "app/idobata-policy-app"
  },
  "body": "この変更は、匿名ユーザー様からのご提案に基づき、マニフェ-スト「１．教育」の章を改善するものです。\n\n**改善点**\n「１）子ども一人ひとりに「専属のAIアシスタント」を届けます」の政策概要内、「AI学習アシスタント」の役割に以下の内容を追記しました。\n「また、生徒の興味や学習の記録をもとに、大学だけでなく、高等専門学校（高専）や専門学校、就職など、多様な進路の選択肢を提示し、早期からのキャリア教育を支援します。」\n\n**改善の意図と目的**\nこの改善は、匿名ユーザー様からいただいた「教育の内容が増え、子どもたちのスケジュールが過密になっている」というご懸念から始まりました。現状の教育では、子どもたちが画一的な進路を目指すことになりがちで、過度な競争や学習負担につながっているのではないか、という問題提起でした。\n\nそこで、子どもたちがより早い段階から、多様な進路の選択肢を知ることの重要性が議論されました。大学進学という道だけでなく、より専門的なスキルを身につけられる高等専門学校（高専）や専門学校、あるいは就職といった、多彩なキャリアパスが存在することを子どもたち自身が認識することが、彼らの可能性を広げ、一人ひとりの個性や興味に合った未来を選択する手助けになると考えます。\n\n今回の変更の目的は、AI学習アシスタントが、学力向上だけでなく、キャリア教育の側面でも子どもたちをサポートする役割を担うことを明確にすることです。AIが客観的なデータ（学習記録や興味関心）に基づき、大学のみならず高専や専門学校などを含む幅広い選択肢を提示することで、子どもや保護者がこれまで知らなかった可能性に気づくきっかけを創出します。これにより、早期から将来について考える文化を育み、画一的な価値観からくるプレッシャーを軽減し、子どもたちが自分自身の道を見つけるための支援を強化することを目指します。\n\n**背景**\nこの提案は、匿名ユーザー様との対話を通じて形成されました。マニフェストが掲げるAI活用が、結果として子どもたちの負担増につながるのではなく、真に一人ひとりの可能性を伸ばすために機能すべきだというご意見をいただきました。特に、国立高専のような優れた教育機関が、大学進学以外の選択肢として十分に認知されていない現状をご指摘いただき、AIアシスタントにその情報提供機能を持たせるという具体的な改善案へと至りました。この変更は、匿名ユーザー様の貴重なご意見を反映したものです。",
  "changedFiles": 1,
  "comments": [],
  "createdAt": "2025-07-08T19:07:07Z",
  "deletions": 0,
  "labels": [
    {
      "id": "LA_kwDOOqTJvM8AAAACAn5d8w",
      "name": "教育",
      "description": "",
      "color": "E57B81"
    }
  ],
  "mergeable": "MERGEABLE",
  "mergedAt": null,
  "number": 4667,
  "reactionGroups": [],
  "state": "OPEN",
  "title": "AIアシスタントによる多様な進路選択支援",
  "updatedAt": "2025-07-09T15:24:16Z",
  "url": "https://github.com/team-mirai/policy/pull/4667",
  "commentsCount": 0,
  "totalReactions": 0
}