{
  "additions": 8,
  "author": {
    "is_bot": true,
    "login": "app/idobata-policy-app"
  },
  "body": "この改善提案は、太一郎様よりいただいた「教員の質を継続的に担保し、子どもたちの安全を断固として守る」という強いご意志をマニフェストに反映させるためのものです。\n\n**提案の背景**\n昨今の報道でも見られるように、教員による不祥事は、子どもたちの心身に深刻な傷を残し、教育現場への信頼を根底から揺るがす重大な問題です。また、教員の資質や指導力に関する懸念も指摘されています。現行の制度では、一度採用された後の教員の質を継続的に評価し、改善を促す仕組みが十分とは言えません。特に、児童生徒に対する性加害などのあってはならない事案を防ぐためには、採用時だけでなく、教員としてのキャリアを通じてその適性を厳しく問う必要があります。\n\n**提案の目的と具体的な内容**\nこの変更は、「２）デジタルによる教員の働き方改革を進めます」の項目に、以下の具体的な施策を追加するものです。\n1.  **AIサポートを前提とした教員免許更新制の導入:** 本マニフェストが掲げるAI等のテクノロジー活用による教員の業務負担軽減を大前提とし、かつて負担の大きさから廃止された免許更新制度を、現代に即した形で再構築・導入します。これにより、教員は常に最新の知識や指導技術を学び続けることが求められ、教育の質の維持・向上を図ります。\n2.  **専門家とAIの協働による公正な学力・適性試験の実施:** 採用選考および免許更新の際に、従来の知識偏重の試験だけでなく、AIのサポートを受けた専門家による多角的な「適性試験」を導入します。これにより、教員としての人格や倫理観、コミュニケーション能力などを客観的かつ公正に評価し、人間性に課題のある人物を教壇から遠ざけます。\n3.  **適性問題が認められた場合の厳格な措置:** 子どもたちを性加害などの危険から断固として守るため、上記の適性試験で著しい問題があると判断された場合には、免許の剥奪を含む厳格な措置を講じることを明記します。これにより、教員を目指す者への強いメッセージとなると同時に、保護者や社会全体の教育への信頼を再構築します。\n\nこの提案は、教員という聖職に就く者に高い倫理観と継続的な自己研鑽を求めると同時に、AIという新たなテクノロジーを活用することで、その評価制度が過度な負担や恣意的な判断に陥ることなく、公正かつ客観的に運用されることを目指すものです。太一郎様の「未来を担う子どもたちのために、教員の質と安全性は決して妥協してはならない」という信念が、この提案のすべての根幹にあります。",
  "changedFiles": 1,
  "comments": [],
  "createdAt": "2025-07-10T11:42:22Z",
  "deletions": 4,
  "labels": [
    {
      "id": "LA_kwDOOqTJvM8AAAACAn5d8w",
      "name": "教育",
      "description": "",
      "color": "E57B81"
    }
  ],
  "mergeable": "MERGEABLE",
  "mergedAt": null,
  "number": 5182,
  "reactionGroups": [],
  "state": "OPEN",
  "title": "【太一郎さんご提案】教員免許制度の改革と採用・評価制度の構築",
  "updatedAt": "2025-07-10T15:21:32Z",
  "url": "https://github.com/team-mirai/policy/pull/5182",
  "commentsCount": 0,
  "totalReactions": 0
}