{
  "additions": 6,
  "author": {
    "is_bot": true,
    "login": "app/idobata-policy-app"
  },
  "body": "匿名ユーザーさんによる改善提案です。\n\n## 提案の概要\n\n本提案は、日本の教育政策を大きく前進させるための2つの重要な柱を提起するものです。第一に、EdTechを最大限に活用し、子ども一人ひとりの学習進度や興味に合わせた「無学年制・科目別習熟度別学習」を導入します。第二に、それを実質的に支えるため、教員を増員し、多様な専門職を学校に配置する「チーム学校」体制を整備し、教育現場への人的投資を強化します。これらの改革により、すべての子どもが自らの才能を最大限に伸ばし、真の「学ぶ権利」を享受できる教育システムの実現を目指します。\n\n## 改善点とその意図・目的\n\n### 1. EdTechを活用した無学年制・科目別習熟度別学習の導入\n\n**目的・背景:**\n現行の画一的な学年制では、学習進度の速い子どもは物足りなさを感じ、逆にゆっくり学びたい子どもは理解が追いつかないまま進級してしまう「学び残し」が発生しています。これは、子どもたちの知的好奇心を削ぎ、学習意欲の低下や、友人関係の構築における困難さの一因ともなっています。特に、学校に行かずに卒業できてしまう現状は、憲法が保障する「教育を受ける権利」を形骸化させかねない深刻な課題です。\n\n**具体的な改善内容:**\nそこで、マニフェストの「３）子どもたちの好奇心と「はじめる力」を育むための教育に投資します」の項目に、以下の政策を追加しました。\n\n> EdTechを活用し、個人の学習進度に合わせた無学年制・科目別習熟度別学習を導入します。これにより、子ども一人ひとりの才能を最大限に伸ばせる環境を整えます。\n>   * 学習のクラスと、HRなどの活動は別に編成することで、多様な友人関係を築ける機会を確保します。\n\nこの制度により、意欲と能力のある子どもは年齢に関わらず進級できる「飛び級」が可能になる一方、学習が遅れがちな子どもは自分のペースで着実に学び直す機会が保障されます。また、学習は習熟度別クラスで行い、ホームルーム等の活動は年齢別のクラスで行うことで、学力向上と社会性の育成を両立させることを目指します。\n\n### 2. 「チーム学校」体制の整備による人的投資の強化\n\n**目的・背景:**\n上記の個別最適な学びを実現するためには、EdTechというツールの導入だけでは不十分です。教員が一人ひとりの子どもに手厚く向き合う時間を確保することが不可欠であり、現在の教員の多忙な状況は喫緊の課題です。\n\n**具体的な改善内容:**\n教員が授業や生徒支援に集中できる環境を整えるため、「１）政府全体で、教育への投資予算を確保します」の項目に、「チーム学校」の概念を具体化する以下の一文を追加しました。\n\n> （前略）教育国債を発行することも検討します。**あわせて、教員の増員、多様な専門職（心理・福祉・ICT専門家など）の配置拡充を進め、教員が子供と向き合う時間を確保するための「チーム学校」体制を整備します。**\n\nこれにより、教員、カウンセラー、ICT支援員といった多様な専門家がチームとして子どもを支える体制を構築します。教員の負担を軽減し、専門性を活かした多角的なサポートを通じて、教育の質そのものを向上させることを目指します。\n\n## 結論\n\nこれらの改善は、単なる制度変更にとどまりません。AI時代に求められる「未来を創る力」を育むというマニフェスト全体のビジョンを具現化するための、具体的かつ強力な手段です。匿名ユーザーさんの問題提起に基づき、すべての子どもたちの可能性を最大限に引き出す、より公正で質の高い教育の実現に向けた提案です。",
  "changedFiles": 1,
  "comments": [],
  "createdAt": "2025-07-13T15:53:48Z",
  "deletions": 1,
  "labels": [
    {
      "id": "LA_kwDOOqTJvM8AAAACAn5d8w",
      "name": "教育",
      "description": "",
      "color": "E57B81"
    }
  ],
  "mergeable": "MERGEABLE",
  "mergedAt": null,
  "number": 6231,
  "reactionGroups": [],
  "state": "OPEN",
  "title": "教育政策の改善案：個別最適化された学びと手厚い支援体制の実現",
  "updatedAt": "2025-07-14T15:24:49Z",
  "url": "https://github.com/team-mirai/policy/pull/6231",
  "commentsCount": 0,
  "totalReactions": 0
}