{
  "additions": 7,
  "author": {
    "is_bot": true,
    "login": "app/idobata-policy-app"
  },
  "body": "**提案者:** ayakaさん\n\n**背景と課題:**\n近年、特別支援教育の必要性は著しく高まっています。しかし、現状の制度では、特別支援学級の擔任は必ずしも専門の免許状（特別支援学校教諭免許状）を保有していなくても担当可能となっています。このため、熱意ある先生方が現場を支えている一方で、教員の専門性や経験にばらつきが生じてしまい、提供される教育の質が必ずしも均一でないという課題が懸念されます。ayakaさんからは、「ニーズが高まっているにも関わらず、質にバラつきがあるのでは」という的確なご指摘をいただきました。子ども一人ひとりの特性に応じた最適な教育を提供するためには、教員の専門性を制度的に担保し、向上させていく仕組みが不可欠です。\n\n**提案内容:**\nこの課題を解決するため、本提案では以下の二つの具体的な施策をマニフェストに追加することを提案します。\n\n1.  **特別支援学級を担当する教員への手当拡充:**\n    専門的な知識やスキルを持つ教員が、その能力を正当に評価され、積極的に特別支援教育に携わることを奨励するために、担当教員への手当を拡充します。これにより、処遇を改善し、質の高い人材の確保と定着を目指します。将来的には「特別支援学校教諭免許状」の保有を必須化することを見据えつつ、まずは魅力的な環境を整備することで、専門性を持つ教員が現場で活躍しやすくなる土壌を育みます。\n\n2.  **担当教員に必須の専門研修・資格制度の導入:**\n    特別支援学級を担当するすべての教員が、一定水準以上の専門知識と指導スキルを身につけることを目指し、必須の研修プログラムと、それに対応する資格制度を新たに導入します。この研修では、発達障害や学習障害など、多様なニーズを持つ子どもたちへの具体的な指導法、保護者との連携方法、関連機関との協力体制の構築など、実践的な内容を盛り込みます。これにより、教員のスキルアップを促し、全国どの地域においても教育の質の標準化と向上を図ります。\n\n**目的と期待される効果:**\n本提案の目的は、特別支援を必要とするすべての子どもたちが、その可能性を最大限に伸ばせるような質の高い教育を受けられる環境を整備することです。手当の拡充と研修・資格制度の導入という二つのアプローチを通じて、教員の専門性を高め、特別支援教育全体の質を底上げします。これにより、子どもたちの健やかな成長を支えるだけでなく、教員自身もやりがいと誇りを持って職務に当たることができるようになり、ひいては日本の教育全体の持続的な発展に貢献するものと考えます。これは、チームみらいが掲げる「誰も取り残さない」社会を実現するための、具体的かつ重要な一歩です。",
  "changedFiles": 2,
  "comments": [
    {
      "id": "IC_kwDOOqTJvM62_bqJ",
      "author": {
        "login": "github-actions"
      },
      "authorAssociation": "NONE",
      "body": "## 📢 X（旧Twitter）通知について\n\nこのPRがマージされると、自動的にX（旧Twitter）に投稿されます。\n\nもし以下のような政策内容の実質的な変更を含まないPRの場合、X通知をスキップすることができます：\n- タイポや誤字脱字の修正\n- マークダウンのフォーマット調整\n- リンク切れの修正\n- その他、政策内容に実質的な変更を含まない修正\n\n### 通知をスキップする方法\nPRに `skip-notification` ラベルを追加してください。\n1. 右側のLabelsセクションをクリック\n2. `skip-notification` を選択\n\n※ Slack通知は内部進捗管理のため、引き続き送信されます。",
      "createdAt": "2025-07-14T15:47:36Z",
      "includesCreatedEdit": false,
      "isMinimized": false,
      "minimizedReason": "",
      "reactionGroups": [],
      "url": "https://github.com/team-mirai/policy/pull/6559#issuecomment-3070081673",
      "viewerDidAuthor": false
    }
  ],
  "createdAt": "2025-07-14T15:47:26Z",
  "deletions": 0,
  "labels": [
    {
      "id": "LA_kwDOOqTJvM8AAAACAn5d8w",
      "name": "教育",
      "description": "",
      "color": "E57B81"
    },
    {
      "id": "LA_kwDOOqTJvM8AAAACAvQ2pA",
      "name": "README",
      "description": "",
      "color": "6F543C"
    }
  ],
  "mergeable": "MERGEABLE",
  "mergedAt": null,
  "number": 6559,
  "reactionGroups": [],
  "state": "OPEN",
  "title": "特別支援教育の質向上に関する提案",
  "updatedAt": "2025-07-15T15:24:00Z",
  "url": "https://github.com/team-mirai/policy/pull/6559",
  "commentsCount": 1,
  "totalReactions": 0
}