{
  "additions": 11,
  "author": {
    "is_bot": true,
    "login": "app/idobata-policy-app"
  },
  "body": "この改善案は、現役の高校教員である匿名ユーザーさんから寄せられた、教育現場の深刻な実態に基づく提案です。現在のマニフェスト案が掲げるEdTech導入や体験学習の拡充といった未来志向の投資に加え、その基盤となる「教員の働きがい」と「学習環境の質」という、極めて重要な二つの側面に対処することを目的としています。\n\n**提案の背景：現場からの悲痛な声**\n\n匿名ユーザーさんからは、日々の業務に追われる中で、教員のなり手不足が常態化し、教育の質そのものが脅かされているという強い危機感が示されました。特に、経験の浅い初任者がいきなり担任を任され、十分な研修も受けられないまま疲弊していく現状は、看過できない問題です。国が「研修制度は整備済み」という認識である一方、現場では多忙さからそれが全く機能していないという乖離も指摘されました。\n\n加えて、学校施設の老朽化も深刻です。雨漏りが放置され、昭和の時代から変わらない備品を使い続けなければならない環境は、教員の労働意欲を削ぐだけでなく、子どもたちの学習環境としても不適切です。さらに、多くの学校が災害時の避難所に指定されているにもかかわらず、その基本的な安全性すら確保できていないという現実は、地域社会全体の課題でもあります。「未来ある若者が、過去に取り残されたような環境で学んでいる」という言葉は、この問題の重さを物語っています。\n\n**改善内容：マニフェストへの新たな項目の追加**\n\nこれらの課題に対応するため、本提案ではマニフェストに新たに「４）教員の「働きがい」を高め、未来のなり手を増やします」という項目を追加しました。主な内容は以下の通りです。\n\n1.  **初任者研修の改革と負担軽減:**\n    初任者が安心して研修に専念できる環境を法的に保障します。具体的には、研修期間中の担任業務や過度な校務を免除し、煩雑な事務作業を抜本的に見直すことで、実践的な指導力と教育への情熱を育むための時間を確保します。これは、単なる「研修の実施」ではなく、「研修が機能する」ための環境整備です。\n\n2.  **未来の創造拠点としての学校施設へ:**\n    学校施設を単なる「箱物」ではなく、「未来の創造拠点」と再定義し、計画的な改修を強力に推進します。Wi-Fiや最新機器の導入といったデジタル環境の整備はもちろん、明るく開放的な職員室、創造性を刺激するような校舎デザインへの刷新を目指します。これにより、教員が誇りを持って働ける魅力的な職場環境を創出し、教職を目指す若者を増やします。また、耐震性の強化や衛生環境の改善も行い、災害時には地域住民が安心して避難できる拠点としての機能も確実に果たせるようにします。\n\n**提案の目的と期待される効果**\n\nこの提案は、教員一人ひとりが教育という仕事に誇りとやりがいを持ち、その能力を最大限に発揮できる環境を整備することが、結果として子どもたちの「未来を創る力」を育む上で最も効果的な投資であるという信念に基づいています。教員のなり手不足という根本問題にアプローチし、教育現場の活力を取り戻すことで、マニフェスト全体が目指す教育ビジョンの実現可能性を大きく高めるものです。匿名ユーザーさんの現場からの貴重な声に端を発したこの改善案が、日本の教育をより良い方向へ導く一助となることを強く願っています。",
  "changedFiles": 1,
  "comments": [
    {
      "id": "IC_kwDOOqTJvM63MPir",
      "author": {
        "login": "github-actions"
      },
      "authorAssociation": "NONE",
      "body": "## 📢 X（旧Twitter）通知について\n\nこのPRがマージされると、自動的にX（旧Twitter）に投稿されます。\n\nもし以下のような政策内容の実質的な変更を含まないPRの場合、X通知をスキップすることができます：\n- タイポや誤字脱字の修正\n- マークダウンのフォーマット調整\n- リンク切れの修正\n- その他、政策内容に実質的な変更を含まない修正\n\n### 通知をスキップする方法\nPRに `skip-notification` ラベルを追加してください。\n1. 右側のLabelsセクションをクリック\n2. `skip-notification` を選択\n\n※ Slack通知は内部進捗管理のため、引き続き送信されます。",
      "createdAt": "2025-07-15T12:38:13Z",
      "includesCreatedEdit": false,
      "isMinimized": false,
      "minimizedReason": "",
      "reactionGroups": [],
      "url": "https://github.com/team-mirai/policy/pull/6869#issuecomment-3073439915",
      "viewerDidAuthor": false
    }
  ],
  "createdAt": "2025-07-15T12:38:06Z",
  "deletions": 1,
  "labels": [
    {
      "id": "LA_kwDOOqTJvM8AAAACAn5d8w",
      "name": "教育",
      "description": "",
      "color": "E57B81"
    }
  ],
  "mergeable": "MERGEABLE",
  "mergedAt": null,
  "number": 6869,
  "reactionGroups": [],
  "state": "OPEN",
  "title": "教育政策：教員の働きがい向上と学校施設の現代化に関する提案",
  "updatedAt": "2025-07-15T15:20:08Z",
  "url": "https://github.com/team-mirai/policy/pull/6869",
  "commentsCount": 1,
  "totalReactions": 0
}